{
	"format_version": "1.8.0",
	"geometry.guardian": {
		"texturewidth": 64,
		"textureheight": 64,
		"visible_bounds_width": 3.5,
		"visible_bounds_height": 3.5,
		"visible_bounds_offset": [0, 1.25, 0],
		"bones": [
			{
				"name": "head11",
				"pivot": [0, 0, 0],
				"mirror": true,
				"cubes": [
					{"origin": [-6, 2, -8], "size": [12, 12, 16], "uv": [0, 0], "mirror": false},
					{"origin": [-8, 2, -6], "size": [2, 12, 12], "uv": [0, 28], "mirror": false},
					{"origin": [6, 2, -6], "size": [2, 12, 12], "uv": [0, 28]},
					{"origin": [-6, 14, -6], "size": [12, 2, 12], "uv": [16, 40]},
					{"origin": [-6, 0, -6], "size": [12, 2, 12], "uv": [16, 40]}
				]
			},
			{
				"name": "head12",
				"parent": "head11",
				"pivot": [0, 0, -11.7]
			},
			{
				"name": "head13",
				"parent": "head12",
				"pivot": [0, 0, -11.7],
				"rotation": [-47.5, 0, 0],
				"cubes": [
					{"origin": [-6, 12, -19.7], "size": [12, 3, 2], "uv": [14, 14]}
				]
			},
			{
				"name": "head14",
				"parent": "head12",
				"pivot": [0, 0, 11.7],
				"rotation": [47.5, 0, 0],
				"cubes": [
					{"origin": [-6, 12.2, 17.5], "size": [12, 3, 2], "uv": [14, 14]}
				]
			},
			{
				"name": "head15",
				"parent": "head11",
				"pivot": [11.8, 0, 0.3],
				"rotation": [0, -90, 0]
			},
			{
				"name": "head16",
				"parent": "head15",
				"pivot": [11.8, 0, 0.3],
				"rotation": [-47.5, 0, 0],
				"cubes": [
					{"origin": [5.8, 12.3, -7.5], "size": [12, 2.8, 2], "uv": [14, 14]}
				]
			},
			{
				"name": "head17",
				"parent": "head15",
				"pivot": [11.8, 0, 23.7],
				"rotation": [47.5, 0, 0],
				"cubes": [
					{"origin": [5.8, 12, 29.7], "size": [12, 3, 2], "uv": [14, 14]}
				]
			},
			{
				"name": "head18",
				"parent": "head11",
				"pivot": [0, 2, -15],
				"rotation": [-10, 0, 0],
				"cubes": [
					{"origin": [-5, 4, -9], "size": [10, 3, 2], "uv": [15, 14]}
				]
			},
			{
				"name": "head19",
				"parent": "head11",
				"pivot": [4, -2, 0],
				"rotation": [0, 0, -26],
				"cubes": [
					{"origin": [9, 0, -6], "size": [3, 6, 12], "uv": [-1, 28], "mirror": true}
				]
			},
			{
				"name": "head20",
				"parent": "head11",
				"pivot": [-4, -2, 0],
				"rotation": [0, 0, 26],
				"cubes": [
					{"origin": [-12, 0, -6], "size": [3, 6, 12], "uv": [-1, 28]}
				]
			},
			{
				"name": "eye2",
				"parent": "head11",
				"pivot": [0, 24, 0],
				"cubes": [
					{"origin": [-1, 6, 0], "size": [2, 2, 1], "uv": [8, 0]}
				]
			},
			{
				"name": "tailpart3",
				"parent": "head11",
				"pivot": [0, 24, 0],
				"cubes": [
					{"origin": [-2, 6, 7], "size": [4, 4, 8], "uv": [40, 0]}
				]
			},
			{
				"name": "tailpart4",
				"parent": "tailpart3",
				"pivot": [0, 24, 0],
				"cubes": [
					{"origin": [0, 7, 0], "size": [3, 3, 7], "uv": [0, 54]}
				]
			},
			{
				"name": "tailpart5",
				"parent": "tailpart4",
				"pivot": [0, 24, 0],
				"cubes": [
					{"origin": [0, 8, 0], "size": [2, 2, 6], "uv": [41, 32]},
					{"origin": [1, 4.5, 3], "size": [1, 9, 9], "uv": [25, 19]}
				]
			},
			{
				"name": "spikepart1",
				"parent": "head11",
				"pivot": [0, 24, 0],
				"cubes": [
					{"origin": [-0.6, 19.5, -0.6], "size": [1.3, 8, 1.1], "uv": [2, 2]},
					{"origin": [-1, 15.5, -1], "size": [2, 7, 2], "uv": [0, 0]}
				]
			},
			{
				"name": "spikepart2",
				"parent": "head11",
				"pivot": [0, 24, 0],
				"cubes": [
					{"origin": [-0.6, 19.5, -0.6], "size": [1.3, 8, 1.1], "uv": [2, 2]},
					{"origin": [-1, 15.5, -1], "size": [2, 7, 2], "uv": [0, 0]}
				]
			},
			{
				"name": "spikepart3",
				"parent": "head11",
				"pivot": [0, 24, 0],
				"cubes": [
					{"origin": [-0.6, 19.5, -0.6], "size": [1.3, 8, 1.1], "uv": [2, 2]},
					{"origin": [-1, 15.5, -1], "size": [2, 7, 2], "uv": [0, 0]}
				]
			},
			{
				"name": "spikepart4",
				"parent": "head11",
				"pivot": [0, 24, 0],
				"cubes": [
					{"origin": [-0.6, 19.5, -0.6], "size": [1.3, 8, 1.1], "uv": [2, 2]},
					{"origin": [-1, 15.5, -1], "size": [2, 7, 2], "uv": [0, 0]}
				]
			},
			{
				"name": "spikepart5",
				"parent": "head11",
				"pivot": [0, 24, 0],
				"cubes": [
					{"origin": [-0.6, 19.5, -0.6], "size": [1.3, 8, 1.1], "uv": [2, 2]},
					{"origin": [-1, 15.5, -1], "size": [2, 7, 2], "uv": [0, 0]}
				]
			},
			{
				"name": "spikepart6",
				"parent": "head11",
				"pivot": [0, 24, 0],
				"cubes": [
					{"origin": [-0.6, 19.5, -0.6], "size": [1.3, 8, 1.1], "uv": [2, 2]},
					{"origin": [-1, 15.5, -1], "size": [2, 7, 2], "uv": [0, 0]}
				]
			},
			{
				"name": "spikepart7",
				"parent": "head11",
				"pivot": [0, 24, 0],
				"cubes": [
					{"origin": [-0.6, 19.5, -0.6], "size": [1.3, 8, 1.1], "uv": [2, 2]},
					{"origin": [-1, 15.5, -1], "size": [2, 7, 2], "uv": [0, 0]}
				]
			},
			{
				"name": "spikepart8",
				"parent": "head11",
				"pivot": [0, 24, 0],
				"cubes": [
					{"origin": [-0.6, 19.5, -0.6], "size": [1.3, 8, 1.1], "uv": [2, 2]},
					{"origin": [-1, 15.5, -1], "size": [2, 7, 2], "uv": [0, 0]}
				]
			},
			{
				"name": "spikepart9",
				"parent": "head11",
				"pivot": [0, 24, 0],
				"cubes": [
					{"origin": [-0.6, 19.5, -0.6], "size": [1.3, 8, 1.1], "uv": [2, 2]},
					{"origin": [-1, 15.5, -1], "size": [2, 7, 2], "uv": [0, 0]}
				]
			},
			{
				"name": "spikepart10",
				"parent": "head11",
				"pivot": [0, 24, 0],
				"cubes": [
					{"origin": [-0.6, 19.5, -0.6], "size": [1.3, 8, 1.1], "uv": [2, 2]},
					{"origin": [-1, 15.5, -1], "size": [2, 7, 2], "uv": [0, 0]}
				]
			},
			{
				"name": "spikepart11",
				"parent": "head11",
				"pivot": [0, 24, 0],
				"cubes": [
					{"origin": [-0.6, 19.5, -0.6], "size": [1.3, 8, 1.1], "uv": [2, 2]},
					{"origin": [-1, 15.5, -1], "size": [2, 7, 2], "uv": [0, 0]}
				]
			},
			{
				"name": "spikepart12",
				"parent": "head11",
				"pivot": [0, 24, 0],
				"cubes": [
					{"origin": [-0.6, 19.5, -0.6], "size": [1.3, 8, 1.1], "uv": [2, 2]},
					{"origin": [-1, 15.5, -1], "size": [2, 7, 2], "uv": [0, 0]}
				]
			}
		]
	}
}